gp6
