Metadata-Version: 1.0
Name: gp6
Version: 0.0.1
Summary: Code for Gaussian Processes aimed at late time cosmological reconstruction
Home-page: https://github.com/reggiebernardo/gp6
Author: Reginald Christian Bernardo
Author-email: reginaldchristianbernardo@gmail.com
License: MIT license
Platform: UNKNOWN
